edcrop/__init__.py
edcrop/__main__.py
edcrop/edcrop.py
edcrop/version.py
edcrop/Example/Weatherdata_S1.edcrop_wf
edcrop/Example/edcrop.yaml
edcrop-1.0.1.dist-info/LICENSE
edcrop-1.0.1.dist-info/METADATA
edcrop-1.0.1.dist-info/WHEEL
edcrop-1.0.1.dist-info/top_level.txt
edcrop-1.0.1.dist-info/RECORD
