Metadata-Version: 2.1
Name: edcrop
Version: 1.0.1
Summary: A Python package to simulate field-scale evapotranspiration and drainage
Author-email: Steen Christensen <sc@geo.au.dk>
License: MIT License
Project-URL: Source Code, https://github.com/SteenChr/edcrop
Project-URL: Online Documentation, https://steenchr.github.io/edcrop
Project-URL: Report with full documentation, https://ebooks.au.dk/aul/catalog/book/539
Keywords: Precipitation,Evapotranspiration,Drainage,Root zone
Classifier: Intended Audience :: Education
Classifier: Intended Audience :: Science/Research
Classifier: Topic :: Scientific/Engineering :: Hydrology
Classifier: Programming Language :: Python :: 3.8
Classifier: License :: OSI Approved :: MIT License
Requires-Python: >=3.8.8
License-File: LICENSE
Requires-Dist: numpy >=1.20.1
Requires-Dist: matplotlib >=3.3.4
Requires-Dist: pandas >=1.2.4
Requires-Dist: pyyaml >=5.4.1
